nairods/tools/__init__.py
nairods/tools/__main__.py
nairods/tools/database.py
nairods/tools/feishu.py
nairods/tools/file.py
nairods/tools/loggertool.py
nairods/tools/time.py
nairods-0.2.0.dist-info/METADATA
nairods-0.2.0.dist-info/WHEEL
nairods-0.2.0.dist-info/entry_points.txt
nairods-0.2.0.dist-info/top_level.txt
nairods-0.2.0.dist-info/RECORD
